odoo9_addon_website_portal_address-9.0.1.0.0-py2.7-nspkg.pth
odoo_addons/website_portal_address/__openerp__.py
odoo_addons/website_portal_address/__init__.py
odoo_addons/website_portal_address/README.rst
odoo_addons/website_portal_address/security/ir.rule.csv
odoo_addons/website_portal_address/i18n/it.po
odoo_addons/website_portal_address/views/contact_address.xml
odoo_addons/website_portal_address/views/layout.xml
odoo_addons/website_portal_address/views/assets.xml
odoo_addons/website_portal_address/controllers/main.py
odoo_addons/website_portal_address/controllers/__init__.py
odoo_addons/website_portal_address/static/description/index.html
odoo_addons/website_portal_address/static/description/multiple_address_option.png
odoo_addons/website_portal_address/static/description/icon.png
odoo_addons/website_portal_address/static/src/js/portal_address.js
odoo9_addon_website_portal_address-9.0.1.0.0.dist-info/top_level.txt
odoo9_addon_website_portal_address-9.0.1.0.0.dist-info/WHEEL
odoo9_addon_website_portal_address-9.0.1.0.0.dist-info/RECORD
odoo9_addon_website_portal_address-9.0.1.0.0.dist-info/metadata.json
odoo9_addon_website_portal_address-9.0.1.0.0.dist-info/DESCRIPTION.rst
odoo9_addon_website_portal_address-9.0.1.0.0.dist-info/METADATA
odoo9_addon_website_portal_address-9.0.1.0.0.dist-info/namespace_packages.txt
