Metadata-Version: 2.0
Name: odoo9-addon-website-portal-address
Version: 9.0.1.0.0
Summary: Contact's Address Manager In Website Portal
Home-page: http://www.serpentcs.com
Author: Serpent Consulting Services Pvt. Ltd.,
Author-email: support@odoo-community.org
License: AGPL-3
Platform: UNKNOWN
Requires-Dist: odoo (<9.1a,>=9.0a)
Requires-Dist: odoo9-addon-website-portal-contact
Classifier: Programming Language :: Python :: 2.7
Classifier: Framework :: Odoo
Classifier: License :: OSI Approved :: GNU Affero General Public License v3
